pycausalmatch/__init__.py
pycausalmatch/__version__.py
pycausalmatch/main.py
pycausalmatch/data/__init__.py
pycausalmatch/data/make_dataset.py
pycausalmatch/features/__init__.py
pycausalmatch/features/build_features.py
pycausalmatch/models/__init__.py
pycausalmatch/models/predict_model.py
pycausalmatch/models/train_model.py
pycausalmatch/visualization/__init__.py
pycausalmatch/visualization/visualize.py
pycausalmatch-0.0.4.dist-info/LICENSE
pycausalmatch-0.0.4.dist-info/METADATA
pycausalmatch-0.0.4.dist-info/WHEEL
pycausalmatch-0.0.4.dist-info/top_level.txt
pycausalmatch-0.0.4.dist-info/RECORD
