Metadata-Version: 2.1
Name: pycausalmatch
Version: 0.0.4
Summary: Causal Impact of an intervention integrated with control group selection
Home-page: https://github.com/unbiasedmodeler/pycausalmatch
Author: Rishi Jumani
Author-email: unbiased.modeler@gmail.com
License: UNKNOWN
Platform: UNKNOWN
Classifier: Programming Language :: Python :: 3.7
Classifier: Programming Language :: Python :: 3.8
Classifier: License :: OSI Approved :: MIT License
Requires-Dist: numpy (>=1.18.1)
Requires-Dist: pandas (>=1.0.3)
Requires-Dist: dtw-python (==1.1.6)
Requires-Dist: tfcausalimpact (==0.0.5)
